judgyprophet/__init__.py
judgyprophet/judgyprophet.py
judgyprophet/stan/build/.buildkeep
judgyprophet/stan/build/.gitkeep
judgyprophet/stan/judgyprophet.stan
judgyprophet/tutorials/__init__.py
judgyprophet/tutorials/resources.py
judgyprophet/utils.py
judgyprophet-0.1.2.dist-info/LICENSE
judgyprophet-0.1.2.dist-info/WHEEL
judgyprophet-0.1.2.dist-info/METADATA
judgyprophet-0.1.2.dist-info/RECORD
