Metadata-Version: 2.1
Name: judgyprophet
Version: 0.1.2
Summary: Forecasting for knowable future events using Bayesian informative priors (forecasting with judgmental-adjustment).
Home-page: https://github.com/AstraZeneca/judgyprophet
License: Apache-2.0
Author: Jack Baker
Author-email: jack.baker@astrazeneca.com
Requires-Python: >=3.8,<3.11
Classifier: License :: OSI Approved :: Apache Software License
Classifier: Programming Language :: Python :: 3
Classifier: Programming Language :: Python :: 3.10
Classifier: Programming Language :: Python :: 3.8
Classifier: Programming Language :: Python :: 3.9
Requires-Dist: numpy (>=1.22.2,<2.0.0)
Requires-Dist: pandas (>=1)
Requires-Dist: pystan (>=2.19.1.1,<2.20.0.0)
Requires-Dist: scipy (>=1.8.0,<2.0.0)
Project-URL: Documentation, https://astrazeneca.github.io/judgyprophet/
Project-URL: Repository, https://github.com/AstraZeneca/judgyprophet
